gismo/__init__.py
gismo/clustering.py
gismo/common.py
gismo/corpus.py
gismo/csr_compress.py
gismo/datasets/__init__.py
gismo/datasets/acm.json.gz
gismo/datasets/acm.py
gismo/datasets/dblp.py
gismo/datasets/reuters.py
gismo/diteration.py
gismo/embedding.py
gismo/filesource.py
gismo/gismo.py
gismo/landmarks.py
gismo/parameters.py
gismo/post_processing.py
gismo/sentencizer.py
gismo-0.5.2.dist-info/AUTHORS.md
gismo-0.5.2.dist-info/METADATA
gismo-0.5.2.dist-info/WHEEL
gismo-0.5.2.dist-info/RECORD
