Metadata-Version: 2.3
Name: gismo
Version: 0.5.2
Summary: GISMO is a NLP tool to rank and organize a corpus of documents according to a query.
License: MIT
Keywords: NLP,Random Walk,D-Iteration,TF-I[D]TF
Author: Fabien Mathieu
Author-email: fabien.mathieu@normalesup.org
Maintainer: Fabien Mathieu
Maintainer-email: fabien.mathieu@normalesup.org
Requires-Python: >=3.10,<3.13
Classifier: Development Status :: 4 - Beta
Classifier: Intended Audience :: Developers
Classifier: Topic :: Software Development :: Build Tools
Classifier: Natural Language :: English
Classifier: Programming Language :: Python :: 3
Classifier: Programming Language :: Python :: 3.10
Classifier: Programming Language :: Python :: 3.11
Classifier: Programming Language :: Python :: 3.12
Provides-Extra: spacy
Requires-Dist: dill (>=0.3.9)
Requires-Dist: en-core-web-sm ; extra == "spacy"
Requires-Dist: lxml (>=5.3.2)
Requires-Dist: numba (>=0.61.2)
Requires-Dist: requests (>=2.32.3)
Requires-Dist: scikit-learn (>=1.6.1)
Requires-Dist: scipy (>=1.15.2)
Requires-Dist: spacy (>=3.8.5,<3.9) ; extra == "spacy"
Requires-Dist: zstandard (>=0.23.0)
Project-URL: Documentation, https://balouf.github.io/gismo/
Project-URL: Repository, https://github.com/balouf/gismo/
